odoo/addons/project_pivot/README.rst
odoo/addons/project_pivot/__init__.py
odoo/addons/project_pivot/__manifest__.py
odoo/addons/project_pivot/i18n/it.po
odoo/addons/project_pivot/i18n/project_pivot.pot
odoo/addons/project_pivot/i18n/pt_BR.po
odoo/addons/project_pivot/readme/CONTRIBUTORS.md
odoo/addons/project_pivot/readme/DESCRIPTION.md
odoo/addons/project_pivot/readme/ROADMAP.md
odoo/addons/project_pivot/static/description/icon.png
odoo/addons/project_pivot/static/description/index.html
odoo/addons/project_pivot/views/project_project.xml
odoo_addon_project_pivot-18.0.1.0.0.3.dist-info/METADATA
odoo_addon_project_pivot-18.0.1.0.0.3.dist-info/WHEEL
odoo_addon_project_pivot-18.0.1.0.0.3.dist-info/top_level.txt
odoo_addon_project_pivot-18.0.1.0.0.3.dist-info/RECORD
